glk.abi3.so
textworld-1.6.2.dist-info/WHEEL
textworld-1.6.2.dist-info/RECORD
textworld-1.6.2.dist-info/top_level.txt
textworld-1.6.2.dist-info/LICENSE.txt
textworld-1.6.2.dist-info/METADATA
textworld-1.6.2.data/scripts/tw-data
textworld-1.6.2.data/scripts/tw-play
textworld-1.6.2.data/scripts/tw-stats
textworld-1.6.2.data/scripts/tw-extract
textworld-1.6.2.data/scripts/tw-make
textworld-1.6.2.data/scripts/tw-view
textworld/testing.py
textworld/core.py
textworld/text_utils.py
textworld/helpers.py
textworld/__init__.py
textworld/utils.py
textworld/version.py
textworld/generator/graph_networks.py
textworld/generator/world.py
textworld/generator/maker.py
textworld/generator/chaining.py
textworld/generator/game.py
textworld/generator/testing.py
textworld/generator/logger.py
textworld/generator/dependency_tree.py
textworld/generator/__init__.py
textworld/generator/text_grammar.py
textworld/generator/vtypes.py
textworld/generator/text_generation.py
textworld/generator/data/__init__.py
textworld/generator/data/logic/thing.twl
textworld/generator/data/logic/room.twl
textworld/generator/data/logic/container.twl
textworld/generator/data/logic/key.twl
textworld/generator/data/logic/inventory.twl
textworld/generator/data/logic/food.twl
textworld/generator/data/logic/supporter.twl
textworld/generator/data/logic/player.twl
textworld/generator/data/logic/door.twl
textworld/generator/data/logic/object.twl
textworld/generator/data/text_grammars/basic_instruction.twg
textworld/generator/data/text_grammars/basic_obj.twg
textworld/generator/data/text_grammars/basic_room.twg
textworld/generator/data/text_grammars/house_room.twg
textworld/generator/data/text_grammars/house_instruction.twg
textworld/generator/data/text_grammars/house_obj.twg
textworld/generator/inform7/world2inform7.py
textworld/generator/inform7/__init__.py
textworld/logic/logic.ebnf
textworld/logic/model.py
textworld/logic/parser.py
textworld/logic/__init__.py
textworld/challenges/registration.py
textworld/challenges/__init__.py
textworld/challenges/utils.py
textworld/challenges/tw_cooking/cooking.py
