Metadata-Version: 2.2
Name: textworld
Version: 1.6.2
Summary: Microsoft Textworld - A Text-based Learning Environment.
Author: Marc-Alexandre Côté
Author-email: Microsoft Textworld <textworld@microsoft.com>
License: TextWorld v1.2
Project-URL: Homepage, https://github.com/microsoft/TextWorld
Project-URL: Issues, https://github.com/microsoft/TextWorld/issues
Classifier: Development Status :: 5 - Production/Stable
Classifier: Intended Audience :: Developers
Classifier: Intended Audience :: Information Technology
Classifier: License :: OSI Approved :: MIT License
Classifier: Natural Language :: English
Classifier: Operating System :: MacOS
Classifier: Operating System :: POSIX
Classifier: Programming Language :: Python :: 3.9
Classifier: Programming Language :: Python :: 3.10
Classifier: Programming Language :: Python :: 3.11
Classifier: Programming Language :: Python :: 3.12
Classifier: Topic :: Scientific/Engineering :: Artificial Life
Requires-Python: >=3.9
License-File: LICENSE.txt
Requires-Dist: numpy>=1.14.5
Requires-Dist: tqdm>=4.17.1
Requires-Dist: cffi>=1.0.0
Requires-Dist: networkx>=2
Requires-Dist: more_itertools
Requires-Dist: tatsu==5.8.3
Requires-Dist: hashids>=1.2.0
Requires-Dist: jericho>=3.3.0
Requires-Dist: mementos>=1.3.1
Requires-Dist: termcolor
Requires-Dist: prompt_toolkit
Provides-Extra: vis
Requires-Dist: pybars3>=0.9.3; extra == "vis"
Requires-Dist: flask>=1.0.2; extra == "vis"
Requires-Dist: selenium<4.3,>=3.12.0; extra == "vis"
Requires-Dist: greenlet>=0.4.13; extra == "vis"
Requires-Dist: gevent>=1.3.5; extra == "vis"
Requires-Dist: pillow>=5.1.0; extra == "vis"
Requires-Dist: plotly<6.0.0,>=4.0.0; extra == "vis"
Requires-Dist: pydot>=1.2.4; extra == "vis"
Requires-Dist: psutil; extra == "vis"
Requires-Dist: matplotlib; extra == "vis"
Provides-Extra: pddl
Requires-Dist: fast-downward-textworld; extra == "pddl"
Provides-Extra: full
Requires-Dist: numpy>=1.14.5; extra == "full"
Requires-Dist: tqdm>=4.17.1; extra == "full"
Requires-Dist: cffi>=1.0.0; extra == "full"
Requires-Dist: networkx>=2; extra == "full"
Requires-Dist: more_itertools; extra == "full"
Requires-Dist: tatsu==5.8.3; extra == "full"
Requires-Dist: hashids>=1.2.0; extra == "full"
Requires-Dist: jericho>=2.2.0; extra == "full"
Requires-Dist: mementos>=1.3.1; extra == "full"
Requires-Dist: termcolor; extra == "full"
Requires-Dist: prompt_toolkit; extra == "full"
Requires-Dist: pybars3>=0.9.3; extra == "full"
Requires-Dist: flask>=1.0.2; extra == "full"
Requires-Dist: selenium<4.3,>=3.12.0; extra == "full"
Requires-Dist: greenlet>=0.4.13; extra == "full"
Requires-Dist: gevent>=1.3.5; extra == "full"
Requires-Dist: pillow>=5.1.0; extra == "full"
Requires-Dist: plotly<6.0.0,>=4.0.0; extra == "full"
Requires-Dist: pydot>=1.2.4; extra == "full"
Requires-Dist: psutil; extra == "full"
Requires-Dist: matplotlib; extra == "full"
Requires-Dist: fast-downward-textworld; extra == "full"
Dynamic: provides-extra
Dynamic: requires-dist
